{"hash":"dd06aaebb0aca2af6e33d7996ce8beaefab4b621","data":{"posts":{"totalCount":32,"pageInfo":{"totalPages":3,"currentPage":3},"edges":[{"node":{"id":"849086d55add77507702cedb1c1b0b25","title":"Everything about the audio tag in HTML and JavaScript","date":"May 28, 2020","summary":"In this article you will learn how to play, pause, stop, rewind, fast forward, audio using JavaScript and HTML","timeToRead":4,"path":"/html-audio"}},{"node":{"id":"81a2d36ef7bf4e82bca648e1e4925b8c","title":"8 ways to use the Spread operator in JavaScript","date":"May 27, 2020","summary":"Spread operator expands an iterable objects into its individual element. An iterable object is anything that you can loop over with our for of loop .","timeToRead":2,"path":"/spread-operator"}}]}},"context":{}}